MANIFEST.in
README.md
VERSION
setup.py
proficloud/__init__.py
proficloud/parallel.py
proficloud.egg-info/PKG-INFO
proficloud.egg-info/SOURCES.txt
proficloud.egg-info/dependency_links.txt
proficloud.egg-info/not-zip-safe
proficloud.egg-info/requires.txt
proficloud.egg-info/top_level.txt
proficloud/analytics/__init__.py
proficloud/analytics/basic.py
proficloud/m2m/__init__.py
proficloud/m2m/mqtt.py
proficloud/ml/AbstractModel.py
proficloud/ml/SomReconstructionError.py
proficloud/ml/StateTiming.py
proficloud/ml/__init__.py
proficloud/tsd_io/__init__.py
proficloud/tsd_io/tsd.py
proficloud/tsd_net/__init__.py
proficloud/tsd_net/ewima.py
proficloud/tsd_net/kairos.py
proficloud/tsd_net/proficloudutil.py
proficloud/tsd_net/stream.py
proficloud/tsd_net/tsd.py