Metadata-Version: 1.0
Name: proficloud
Version: 3.1.1
Summary: Easy access for PROFICLOUD
Home-page: https://proficloud.atlassian.net/wiki/spaces/PP/overview
Author: Proficloud
Author-email: proficloud@proficloud.net
License: GPLv3
Platform: UNKNOWN
